automacao_utils/__init__.py
automacao_utils/download_utils.py
automacao_utils/mover_arquivo_utils.py
automacao_utils/notificacao_utils.py
automacao_utils/selenium_utils.py
utils_global-1.9.0.dist-info/METADATA
utils_global-1.9.0.dist-info/WHEEL
utils_global-1.9.0.dist-info/top_level.txt
utils_global-1.9.0.dist-info/RECORD
