Metadata-Version: 2.4
Name: utils-global
Version: 1.9.0
Summary: Biblioteca de funções úteis para automações com Selenium. Fornece utilitários para manipulação de arquivos, downloads e interações com Selenium.
Requires-Python: >=3.13
Requires-Dist: build>=1.2.2.post1
Requires-Dist: psutil>=7.0.0
Requires-Dist: seleniumbase>=4.38.2
Requires-Dist: twine>=6.1.0
Requires-Dist: watchdog>=6.0.0
